dd-0.5.6.dist-info/WHEEL
dd-0.5.6.dist-info/METADATA
dd-0.5.6.dist-info/RECORD
dd-0.5.6.dist-info/top_level.txt
dd-0.5.6.dist-info/LICENSE
dd/bdd_parsetab.py
dd/PYTHON_LICENSE
dd/cudd.cpython-39-x86_64-linux-gnu.so
dd/GLIBC_COPYING.LIB
dd/_version.py
dd/cudd.c
dd/cudd_zdd.c
dd/_parser.py
dd/dddmp.py
dd/mdd.py
dd/bdd.py
dd/_copy.py
dd/_utils.py
dd/buddy_.pxd
dd/_cudd_addendum.c
dd/autoref.py
dd/_compat.py
dd/dddmp_parsetab.py
dd/cudd.pyx
dd/cudd_zdd.cpython-39-x86_64-linux-gnu.so
dd/buddy.pyx
dd/GLIBC_LICENSES
dd/CUDD_LICENSE
dd/__init__.py
dd/c_sylvan.pxd
dd/_abc.py
dd/sylvan.pyx
dd/cudd_zdd.pyx
