Metadata-Version: 2.1
Name: dd
Version: 0.5.6
Summary: Binary decision diagrams implemented in pure Python, as well as Cython wrappers of CUDD, Sylvan, and BuDDy.
Home-page: https://github.com/tulip-control/dd
Author: Caltech Control and Dynamical Systems
Author-email: tulip@tulip-control.org
License: BSD
Keywords: bdd,binary decision diagram,decision diagram,boolean,networkx,dot
Platform: UNKNOWN
Classifier: Development Status :: 2 - Pre-Alpha
Classifier: Intended Audience :: Developers
Classifier: Intended Audience :: Science/Research
Classifier: License :: OSI Approved :: BSD License
Classifier: Operating System :: OS Independent
Classifier: Programming Language :: Cython
Classifier: Programming Language :: Python
Classifier: Programming Language :: Python :: 2
Classifier: Programming Language :: Python :: 2.7
Classifier: Programming Language :: Python :: 3
Classifier: Programming Language :: Python :: 3.5
Classifier: Programming Language :: Python :: 3.6
Classifier: Programming Language :: Python :: 3.7
Classifier: Programming Language :: Python :: 3.8
Classifier: Programming Language :: Python :: 3.9
Classifier: Topic :: Scientific/Engineering
Classifier: Topic :: Software Development
Requires-Dist: astutils (>=0.0.1)
Requires-Dist: networkx (>=1.9.1)
Requires-Dist: ply (<=3.10,>=3.4)
Requires-Dist: psutil (>=3.2.2)
Requires-Dist: pydot (>=1.2.2)
Requires-Dist: setuptools (>=19.6)
